silverbp_artifactory/__init__.py
silverbp_artifactory/artifactory.py
silverbp_artifactory-0.2.3.dist-info/DESCRIPTION.rst
silverbp_artifactory-0.2.3.dist-info/METADATA
silverbp_artifactory-0.2.3.dist-info/RECORD
silverbp_artifactory-0.2.3.dist-info/WHEEL
silverbp_artifactory-0.2.3.dist-info/metadata.json
silverbp_artifactory-0.2.3.dist-info/top_level.txt
