Metadata-Version: 2.0
Name: silverbp-artifactory
Version: 0.2.3
Summary: Python API for interacting with Artifactory
Home-page: https://github.com/silverbp/pypi-artifactory
Author: Silver Blueprints LLC
Author-email: admin@silverblueprints.com
License: MIT
Platform: UNKNOWN
